setup.cfg
setup.py
CMakeHelp.egg-info/PKG-INFO
CMakeHelp.egg-info/SOURCES.txt
CMakeHelp.egg-info/dependency_links.txt
CMakeHelp.egg-info/entry_points.txt
CMakeHelp.egg-info/not-zip-safe
CMakeHelp.egg-info/top_level.txt
cmakehelp/__init__.py
cmakehelp/cmakehelp.py