Metadata-Version: 1.0
Name: CMakeHelp
Version: 0.1dev
Summary: CMake Interactive Help System
Home-page: http://www.qtzlabs.com/
Author: Tomasz Bogdal
Author-email: vladsmailtotomas@gmail.com
License: LGPL
Keywords: cmake interactive help system command line
Platform: UNKNOWN
